FreeMobileConso/__init__.py
FreeMobileConso/client.py
FreeMobileConso/dataClassification.py
FreeMobileConso-0.1.2.dist-info/LICENSE
FreeMobileConso-0.1.2.dist-info/METADATA
FreeMobileConso-0.1.2.dist-info/WHEEL
FreeMobileConso-0.1.2.dist-info/top_level.txt
FreeMobileConso-0.1.2.dist-info/RECORD
