Metadata-Version: 2.1
Name: FreeMobileConso
Version: 0.1.2
Summary: A python API for get your consommation of your Free mobile account
Home-page: https://github.com/CorentinMre/FreeMobileConso
Author: CorentinMre
Author-email: corentin.marie@isen-ouest.yncrea.fr
License: MIT
Classifier: Programming Language :: Python :: 3
Classifier: License :: OSI Approved :: MIT License
Classifier: Operating System :: OS Independent
License-File: LICENSE
Requires-Dist: requests
Requires-Dist: bs4
